tileset_analyzer/__debug__ .py
tileset_analyzer/__init__.py
tileset_analyzer/__main__.py
tileset_analyzer/main.py
tileset_analyzer/api/__init__.py
tileset_analyzer/api/main_api.py
tileset_analyzer/api/tile_serve_source/__init__.py
tileset_analyzer/api/tile_serve_source/tile_serve_source_repository.py
tileset_analyzer/api/tile_serve_source/folder_tiles/__init__.py
tileset_analyzer/api/tile_serve_source/folder_tiles/folder_serve_source.py
tileset_analyzer/api/tile_serve_source/mbtiles/__init__.py
tileset_analyzer/api/tile_serve_source/mbtiles/mbtiles_serve_source.py
tileset_analyzer/data_source/__init__.py
tileset_analyzer/data_source/ds_utils.py
tileset_analyzer/data_source/tile_source.py
tileset_analyzer/data_source/tile_source_factory.py
tileset_analyzer/data_source/folder_tiles/__init__.py
tileset_analyzer/data_source/folder_tiles/folder_tiles_source.py
tileset_analyzer/data_source/folder_tiles/folder_utils.py
tileset_analyzer/data_source/mbtiles/__init__.py
tileset_analyzer/data_source/mbtiles/mbtiles_source.py
tileset_analyzer/data_source/mbtiles/sql_queries.py
tileset_analyzer/data_source/mbtiles/sqllite_utils.py
tileset_analyzer/entities/__init__.py
tileset_analyzer/entities/job_param.py
tileset_analyzer/entities/layer_info.py
tileset_analyzer/entities/layer_level_size.py
tileset_analyzer/entities/level_count.py
tileset_analyzer/entities/level_size.py
tileset_analyzer/entities/tile_item.py
tileset_analyzer/entities/tileset_analysis_result.py
tileset_analyzer/entities/tileset_info.py
tileset_analyzer/readers/__init__.py
tileset_analyzer/readers/vector_tile/__init__.py
tileset_analyzer/readers/vector_tile/engine.py
tileset_analyzer/readers/vector_tile/vector_tile_pb2.py
tileset_analyzer/static/data/.gitkeep
tileset_analyzer/static/ui/asset-manifest.json
tileset_analyzer/static/ui/favicon.ico
tileset_analyzer/static/ui/index.html
tileset_analyzer/static/ui/logo.png
tileset_analyzer/static/ui/logo192.png
tileset_analyzer/static/ui/logo512.png
tileset_analyzer-0.0.70.dist-info/METADATA
tileset_analyzer-0.0.70.dist-info/WHEEL
tileset_analyzer-0.0.70.dist-info/entry_points.txt
tileset_analyzer-0.0.70.dist-info/top_level.txt
tileset_analyzer-0.0.70.dist-info/RECORD
