Metadata-Version: 2.1
Name: tileset_analyzer
Version: 0.0.70
Summary: Analyze vector Tileset
Home-page: https://github.com/geoyogesh/tileset_analyzer
Author: Yogesh Dhanapal
Author-email: geoyogesh@gmail.com
License: MIT
Classifier: Operating System :: OS Independent
Classifier: Programming Language :: Python :: 3.6
Classifier: Programming Language :: Python :: 3.7
Classifier: Programming Language :: Python :: 3.8
Classifier: Programming Language :: Python :: 3.9
Requires-Python: >=3.9, <4
Requires-Dist: fastapi
Requires-Dist: uvicorn[standard]
Requires-Dist: pandas
Requires-Dist: protobuf <=3.20.3
Requires-Dist: parse
